starconsumers/__init__.py
starconsumers/__main__.py
starconsumers/applications.py
starconsumers/cli/__init__.py
starconsumers/cli/discover.py
starconsumers/cli/main.py
starconsumers/cli/runner.py
starconsumers/consumers.py
starconsumers/datastructures.py
starconsumers/exceptions.py
starconsumers/logger.py
starconsumers/middlewares.py
starconsumers/observability.py
starconsumers/process.py
starconsumers/pubsub/__init__.py
starconsumers/pubsub/publisher.py
starconsumers/pubsub/subscriber.py
starconsumers/pubsub/utils.py
starconsumers/py.typed
starconsumers-0.2.3.dist-info/WHEEL
starconsumers-0.2.3.dist-info/entry_points.txt
starconsumers-0.2.3.dist-info/METADATA
starconsumers-0.2.3.dist-info/RECORD
